[
  {
    "formula_id": "formula_001",
    "block_id": "b0049",
    "page": 3,
    "bbox": [
      0.45,
      0.861,
      0.825,
      0.875
    ],
    "crop_required": true,
    "overlay_required": true,
    "crop_path": "formula_crops/formula_001_p3.png",
    "overlay_path": "formula_overlays/formula_001_page_3.png",
    "section": "Related Work",
    "section_confidence": "medium",
    "section_reason": "reading_order_context: page 3",
    "block_source": "mineru25pro",
    "mineru_latex": "v _ {\\text { vehicle }} = r \\cdot \\omega \\tag {1}",
    "marker_latex": "",
    "final_latex": "v _ {\\text { vehicle }} = r \\cdot \\omega \\tag {1}",
    "final_origin": "mineru_latex",
    "risk_flags": []
  },
  {
    "formula_id": "formula_002",
    "block_id": "b0070",
    "page": 4,
    "bbox": [
      0.462,
      0.814,
      0.825,
      0.83
    ],
    "crop_required": true,
    "overlay_required": true,
    "crop_path": "formula_crops/formula_002_p4.png",
    "overlay_path": "formula_overlays/formula_002_page_4.png",
    "section": "Related Work",
    "section_confidence": "medium",
    "section_reason": "reading_order_context: page 4",
    "block_source": "mineru25pro",
    "mineru_latex": "P = V \\cdot I \\tag {2}",
    "marker_latex": "",
    "final_latex": "P = V \\cdot I \\tag {2}",
    "final_origin": "mineru_latex",
    "risk_flags": []
  },
  {
    "formula_id": "formula_003",
    "block_id": "b0084",
    "page": 6,
    "bbox": [
      0.375,
      0.463,
      0.826,
      0.499
    ],
    "crop_required": true,
    "overlay_required": true,
    "crop_path": "formula_crops/formula_003_p6.png",
    "overlay_path": "formula_overlays/formula_003_page_6.png",
    "section": "Related Work",
    "section_confidence": "medium",
    "section_reason": "reading_order_context: page 6",
    "block_source": "mineru25pro",
    "mineru_latex": "\\begin{array}{l} \\mathcal {L} _ {\\theta , \\phi} (\\mathbf {X}) = \\mathbb {E} _ {\\mathbf {Z} \\sim q _ {\\phi} (\\mathbf {Z} | \\mathbf {X})} \\left[ \\log p _ {\\theta} (\\mathbf {X} | \\mathbf {Z}) \\right] \\tag {3} \\\\ - D _ {\\mathrm{KL}} \\left(q _ {\\phi} (\\mathbf {Z} | \\mathbf {X}) \\mid \\mid p _ {\\theta} (\\mathbf {Z})\\right) \\\\ \\end{array}",
    "marker_latex": "",
    "final_latex": "\\begin{array}{l} \\mathcal {L} _ {\\theta , \\phi} (\\mathbf {X}) = \\mathbb {E} _ {\\mathbf {Z} \\sim q _ {\\phi} (\\mathbf {Z} | \\mathbf {X})} \\left[ \\log p _ {\\theta} (\\mathbf {X} | \\mathbf {Z}) \\right] \\tag {3} \\\\ - D _ {\\mathrm{KL}} \\left(q _ {\\phi} (\\mathbf {Z} | \\mathbf {X}) \\mid \\mid p _ {\\theta} (\\mathbf {Z})\\right) \\\\ \\end{array}",
    "final_origin": "mineru_latex",
    "risk_flags": []
  },
  {
    "formula_id": "formula_004",
    "block_id": "b0086",
    "page": 6,
    "bbox": [
      0.435,
      0.566,
      0.826,
      0.582
    ],
    "crop_required": true,
    "overlay_required": true,
    "crop_path": "formula_crops/formula_004_p6.png",
    "overlay_path": "formula_overlays/formula_004_page_6.png",
    "section": "Related Work",
    "section_confidence": "medium",
    "section_reason": "reading_order_context: page 6",
    "block_source": "mineru25pro",
    "mineru_latex": "\\mathcal {L} _ {\\mathrm{VAE}} = - \\mathcal {L} _ {\\theta , \\phi} (\\mathbf {X}) \\tag {4}",
    "marker_latex": "",
    "final_latex": "\\mathcal {L} _ {\\mathrm{VAE}} = - \\mathcal {L} _ {\\theta , \\phi} (\\mathbf {X}) \\tag {4}",
    "final_origin": "mineru_latex",
    "risk_flags": []
  },
  {
    "formula_id": "formula_005",
    "block_id": "b0088",
    "page": 6,
    "bbox": [
      0.44,
      0.655,
      0.825,
      0.671
    ],
    "crop_required": true,
    "overlay_required": true,
    "crop_path": "formula_crops/formula_005_p6.png",
    "overlay_path": "formula_overlays/formula_005_page_6.png",
    "section": "Related Work",
    "section_confidence": "medium",
    "section_reason": "reading_order_context: page 6",
    "block_source": "mineru25pro",
    "mineru_latex": "\\mathbf {Z} = \\boldsymbol {\\mu} _ {\\mathbf {Z}} + \\epsilon \\cdot \\boldsymbol {\\sigma} _ {\\mathbf {Z}} \\tag {5}",
    "marker_latex": "",
    "final_latex": "\\mathbf {Z} = \\boldsymbol {\\mu} _ {\\mathbf {Z}} + \\epsilon \\cdot \\boldsymbol {\\sigma} _ {\\mathbf {Z}} \\tag {5}",
    "final_origin": "mineru_latex",
    "risk_flags": []
  },
  {
    "formula_id": "formula_006",
    "block_id": "b0093",
    "page": 6,
    "bbox": [
      0.408,
      0.839,
      0.826,
      0.88
    ],
    "crop_required": true,
    "overlay_required": true,
    "crop_path": "formula_crops/formula_006_p6.png",
    "overlay_path": "formula_overlays/formula_006_page_6.png",
    "section": "Related Work",
    "section_confidence": "medium",
    "section_reason": "reading_order_context: page 6",
    "block_source": "mineru25pro",
    "mineru_latex": "\\mathbf {C} = \\text { Softmax } \\left(\\frac {\\mathbf {Q} \\mathbf {K} ^ {T}}{\\sqrt {d _ {\\mathbf {K}}}}\\right) \\mathbf {V} \\tag {6}",
    "marker_latex": "",
    "final_latex": "\\mathbf {C} = \\text { Softmax } \\left(\\frac {\\mathbf {Q} \\mathbf {K} ^ {T}}{\\sqrt {d _ {\\mathbf {K}}}}\\right) \\mathbf {V} \\tag {6}",
    "final_origin": "mineru_latex",
    "risk_flags": []
  },
  {
    "formula_id": "formula_007",
    "block_id": "b0098",
    "page": 7,
    "bbox": [
      0.342,
      0.206,
      0.826,
      0.226
    ],
    "crop_required": true,
    "overlay_required": true,
    "crop_path": "formula_crops/formula_007_p7.png",
    "overlay_path": "formula_overlays/formula_007_page_7.png",
    "section": "Related Work",
    "section_confidence": "medium",
    "section_reason": "reading_order_context: page 7",
    "block_source": "mineru25pro",
    "mineru_latex": "\\mathbf {Q} _ {i} = \\mathbf {Q} \\mathbf {W} _ {i} ^ {Q} \\quad \\mathbf {K} _ {i} = \\mathbf {K} \\mathbf {W} _ {i} ^ {K} \\quad \\mathbf {V} _ {i} = \\mathbf {V} \\mathbf {W} _ {i} ^ {V} \\tag {7}",
    "marker_latex": "",
    "final_latex": "\\mathbf {Q} _ {i} = \\mathbf {Q} \\mathbf {W} _ {i} ^ {Q} \\quad \\mathbf {K} _ {i} = \\mathbf {K} \\mathbf {W} _ {i} ^ {K} \\quad \\mathbf {V} _ {i} = \\mathbf {V} \\mathbf {W} _ {i} ^ {V} \\tag {7}",
    "final_origin": "mineru_latex",
    "risk_flags": []
  },
  {
    "formula_id": "formula_008",
    "block_id": "b0100",
    "page": 7,
    "bbox": [
      0.4,
      0.267,
      0.826,
      0.309
    ],
    "crop_required": true,
    "overlay_required": true,
    "crop_path": "formula_crops/formula_008_p7.png",
    "overlay_path": "formula_overlays/formula_008_page_7.png",
    "section": "Related Work",
    "section_confidence": "medium",
    "section_reason": "reading_order_context: page 7",
    "block_source": "mineru25pro",
    "mineru_latex": "\\mathbf {C} _ {i} = \\text { Softmax } \\left(\\frac {\\mathbf {Q} _ {i} \\mathbf {K} _ {i} ^ {T}}{\\sqrt {d _ {\\mathbf {K}}}}\\right) \\mathbf {V} _ {i} \\tag {8}",
    "marker_latex": "",
    "final_latex": "\\mathbf {C} _ {i} = \\text { Softmax } \\left(\\frac {\\mathbf {Q} _ {i} \\mathbf {K} _ {i} ^ {T}}{\\sqrt {d _ {\\mathbf {K}}}}\\right) \\mathbf {V} _ {i} \\tag {8}",
    "final_origin": "mineru_latex",
    "risk_flags": []
  },
  {
    "formula_id": "formula_009",
    "block_id": "b0102",
    "page": 7,
    "bbox": [
      0.427,
      0.353,
      0.826,
      0.372
    ],
    "crop_required": true,
    "overlay_required": true,
    "crop_path": "formula_crops/formula_009_p7.png",
    "overlay_path": "formula_overlays/formula_009_page_7.png",
    "section": "Related Work",
    "section_confidence": "medium",
    "section_reason": "reading_order_context: page 7",
    "block_source": "mineru25pro",
    "mineru_latex": "\\mathbf {C} = \\left[ \\mathbf {C} _ {1}, \\dots , \\mathbf {C} _ {h} \\right] \\mathbf {W} ^ {O} \\tag {9}",
    "marker_latex": "",
    "final_latex": "\\mathbf {C} = \\left[ \\mathbf {C} _ {1}, \\dots , \\mathbf {C} _ {h} \\right] \\mathbf {W} ^ {O} \\tag {9}",
    "final_origin": "mineru_latex",
    "risk_flags": []
  },
  {
    "formula_id": "formula_010",
    "block_id": "b0108",
    "page": 7,
    "bbox": [
      0.414,
      0.72,
      0.825,
      0.735
    ],
    "crop_required": true,
    "overlay_required": true,
    "crop_path": "formula_crops/formula_010_p7.png",
    "overlay_path": "formula_overlays/formula_010_page_7.png",
    "section": "Related Work",
    "section_confidence": "medium",
    "section_reason": "reading_order_context: page 7",
    "block_source": "mineru25pro",
    "mineru_latex": "\\eta_ {t} = \\mathrm{SVR} (\\mu_ {\\mathbf {z}, t}, \\sigma_ {\\mathbf {z}, t}) + c \\tag {10}",
    "marker_latex": "",
    "final_latex": "\\eta_ {t} = \\mathrm{SVR} (\\mu_ {\\mathbf {z}, t}, \\sigma_ {\\mathbf {z}, t}) + c \\tag {10}",
    "final_origin": "mineru_latex",
    "risk_flags": []
  },
  {
    "formula_id": "formula_011",
    "block_id": "b0111",
    "page": 7,
    "bbox": [
      0.389,
      0.842,
      0.826,
      0.861
    ],
    "crop_required": true,
    "overlay_required": true,
    "crop_path": "formula_crops/formula_011_p7.png",
    "overlay_path": "formula_overlays/formula_011_page_7.png",
    "section": "Related Work",
    "section_confidence": "medium",
    "section_reason": "reading_order_context: page 7",
    "block_source": "mineru25pro",
    "mineru_latex": "f ^ {k} \\left(\\mathbf {z} _ {t} ^ {k - 1}\\right) = \\mathbf {u} \\tanh \\left(\\mathbf {w} \\mathbf {z} _ {t} ^ {k - 1}\\right) + \\mathbf {b} \\tag {11}",
    "marker_latex": "",
    "final_latex": "f ^ {k} \\left(\\mathbf {z} _ {t} ^ {k - 1}\\right) = \\mathbf {u} \\tanh \\left(\\mathbf {w} \\mathbf {z} _ {t} ^ {k - 1}\\right) + \\mathbf {b} \\tag {11}",
    "final_origin": "mineru_latex",
    "risk_flags": []
  },
  {
    "formula_id": "formula_012",
    "block_id": "b0116",
    "page": 8,
    "bbox": [
      0.335,
      0.208,
      0.826,
      0.227
    ],
    "crop_required": true,
    "overlay_required": true,
    "crop_path": "formula_crops/formula_012_p8.png",
    "overlay_path": "formula_overlays/formula_012_page_8.png",
    "section": "Related Work",
    "section_confidence": "medium",
    "section_reason": "reading_order_context: page 8",
    "block_source": "mineru25pro",
    "mineru_latex": "W _ {i} \\left(\\mathbf {z} _ {\\text {test}}, \\mathbf {z} _ {i}\\right) = \\left\\| \\mu_ {\\mathbf {z} _ {\\text {test}}} - \\mu_ {\\mathbf {z} _ {i}} \\right\\| _ {2} ^ {2} + \\left\\| \\Sigma_ {\\mathbf {z} _ {\\text {test}}} ^ {1 / 2} - \\Sigma_ {\\mathbf {z} _ {i}} ^ {1 / 2} \\right\\| _ {F} ^ {2} \\tag {12}",
    "marker_latex": "",
    "final_latex": "W _ {i} \\left(\\mathbf {z} _ {\\text {test}}, \\mathbf {z} _ {i}\\right) = \\left\\| \\mu_ {\\mathbf {z} _ {\\text {test}}} - \\mu_ {\\mathbf {z} _ {i}} \\right\\| _ {2} ^ {2} + \\left\\| \\Sigma_ {\\mathbf {z} _ {\\text {test}}} ^ {1 / 2} - \\Sigma_ {\\mathbf {z} _ {i}} ^ {1 / 2} \\right\\| _ {F} ^ {2} \\tag {12}",
    "final_origin": "mineru_latex",
    "risk_flags": []
  },
  {
    "formula_id": "formula_013",
    "block_id": "b0126",
    "page": 8,
    "bbox": [
      0.424,
      0.761,
      0.826,
      0.779
    ],
    "crop_required": true,
    "overlay_required": true,
    "crop_path": "formula_crops/formula_013_p8.png",
    "overlay_path": "formula_overlays/formula_013_page_8.png",
    "section": "Method",
    "section_confidence": "medium",
    "section_reason": "reading_order_context: page 8",
    "block_source": "mineru25pro",
    "mineru_latex": "\\left(\\boldsymbol {\\mu} _ {\\mathbf {Z}}, \\log \\boldsymbol {\\sigma} _ {\\mathbf {Z}} ^ {2}\\right) = q _ {\\phi} (\\mathbf {X}) \\tag {13}",
    "marker_latex": "",
    "final_latex": "\\left(\\boldsymbol {\\mu} _ {\\mathbf {Z}}, \\log \\boldsymbol {\\sigma} _ {\\mathbf {Z}} ^ {2}\\right) = q _ {\\phi} (\\mathbf {X}) \\tag {13}",
    "final_origin": "mineru_latex",
    "risk_flags": []
  },
  {
    "formula_id": "formula_014",
    "block_id": "b0128",
    "page": 8,
    "bbox": [
      0.421,
      0.829,
      0.826,
      0.846
    ],
    "crop_required": true,
    "overlay_required": true,
    "crop_path": "formula_crops/formula_014_p8.png",
    "overlay_path": "formula_overlays/formula_014_page_8.png",
    "section": "Method",
    "section_confidence": "medium",
    "section_reason": "reading_order_context: page 8",
    "block_source": "mineru25pro",
    "mineru_latex": "\\mathbf {Z} \\sim \\mathcal {N} \\left(\\boldsymbol {\\mu} _ {\\mathbf {Z}}, \\operatorname{diag} \\left(\\boldsymbol {\\sigma} _ {\\mathbf {Z}}\\right)\\right) \\tag {14}",
    "marker_latex": "",
    "final_latex": "\\mathbf {Z} \\sim \\mathcal {N} \\left(\\boldsymbol {\\mu} _ {\\mathbf {Z}}, \\operatorname{diag} \\left(\\boldsymbol {\\sigma} _ {\\mathbf {Z}}\\right)\\right) \\tag {14}",
    "final_origin": "mineru_latex",
    "risk_flags": []
  },
  {
    "formula_id": "formula_015",
    "block_id": "b0130",
    "page": 8,
    "bbox": [
      0.344,
      0.894,
      0.826,
      0.914
    ],
    "crop_required": true,
    "overlay_required": true,
    "crop_path": "formula_crops/formula_015_p8.png",
    "overlay_path": "formula_overlays/formula_015_page_8.png",
    "section": "Method",
    "section_confidence": "medium",
    "section_reason": "reading_order_context: page 8",
    "block_source": "mineru25pro",
    "mineru_latex": "\\mathbf {Q} _ {i} = \\mathbf {X} \\mathbf {W} _ {i} ^ {Q} \\quad \\mathbf {K} _ {i} = \\mathbf {X} \\mathbf {W} _ {i} ^ {K} \\quad \\mathbf {V} _ {i} = \\mathbf {Z} \\mathbf {W} _ {i} ^ {V} \\tag {15}",
    "marker_latex": "",
    "final_latex": "\\mathbf {Q} _ {i} = \\mathbf {X} \\mathbf {W} _ {i} ^ {Q} \\quad \\mathbf {K} _ {i} = \\mathbf {X} \\mathbf {W} _ {i} ^ {K} \\quad \\mathbf {V} _ {i} = \\mathbf {Z} \\mathbf {W} _ {i} ^ {V} \\tag {15}",
    "final_origin": "mineru_latex",
    "risk_flags": []
  },
  {
    "formula_id": "formula_016",
    "block_id": "b0133",
    "page": 9,
    "bbox": [
      0.4,
      0.125,
      0.826,
      0.165
    ],
    "crop_required": true,
    "overlay_required": true,
    "crop_path": "formula_crops/formula_016_p9.png",
    "overlay_path": "formula_overlays/formula_016_page_9.png",
    "section": "Method",
    "section_confidence": "medium",
    "section_reason": "reading_order_context: page 9",
    "block_source": "mineru25pro",
    "mineru_latex": "\\mathbf {C} _ {i} = \\text { Softmax } \\left(\\frac {\\mathbf {Q} _ {i} \\mathbf {K} _ {i} ^ {T}}{\\sqrt {d _ {\\mathbf {K}}}}\\right) \\mathbf {V} _ {i} \\tag {16}",
    "marker_latex": "",
    "final_latex": "\\mathbf {C} _ {i} = \\text { Softmax } \\left(\\frac {\\mathbf {Q} _ {i} \\mathbf {K} _ {i} ^ {T}}{\\sqrt {d _ {\\mathbf {K}}}}\\right) \\mathbf {V} _ {i} \\tag {16}",
    "final_origin": "mineru_latex",
    "risk_flags": []
  },
  {
    "formula_id": "formula_017",
    "block_id": "b0135",
    "page": 9,
    "bbox": [
      0.427,
      0.203,
      0.826,
      0.221
    ],
    "crop_required": true,
    "overlay_required": true,
    "crop_path": "formula_crops/formula_017_p9.png",
    "overlay_path": "formula_overlays/formula_017_page_9.png",
    "section": "Method",
    "section_confidence": "medium",
    "section_reason": "reading_order_context: page 9",
    "block_source": "mineru25pro",
    "mineru_latex": "\\mathbf {C} = \\left[ \\mathbf {C} _ {1}, \\dots , \\mathbf {C} _ {h} \\right] \\mathbf {W} ^ {O} \\tag {17}",
    "marker_latex": "",
    "final_latex": "\\mathbf {C} = \\left[ \\mathbf {C} _ {1}, \\dots , \\mathbf {C} _ {h} \\right] \\mathbf {W} ^ {O} \\tag {17}",
    "final_origin": "mineru_latex",
    "risk_flags": []
  },
  {
    "formula_id": "formula_018",
    "block_id": "b0137",
    "page": 9,
    "bbox": [
      0.423,
      0.259,
      0.826,
      0.276
    ],
    "crop_required": true,
    "overlay_required": true,
    "crop_path": "formula_crops/formula_018_p9.png",
    "overlay_path": "formula_overlays/formula_018_page_9.png",
    "section": "Method",
    "section_confidence": "medium",
    "section_reason": "reading_order_context: page 9",
    "block_source": "mineru25pro",
    "mineru_latex": "\\left(\\boldsymbol {\\mu} _ {\\mathbf {X}}, \\log \\sigma_ {\\mathbf {X}} ^ {2}\\right) = p _ {\\theta} (\\mathbf {C}) \\tag {18}",
    "marker_latex": "",
    "final_latex": "\\left(\\boldsymbol {\\mu} _ {\\mathbf {X}}, \\log \\sigma_ {\\mathbf {X}} ^ {2}\\right) = p _ {\\theta} (\\mathbf {C}) \\tag {18}",
    "final_origin": "mineru_latex",
    "risk_flags": []
  },
  {
    "formula_id": "formula_019",
    "block_id": "b0141",
    "page": 9,
    "bbox": [
      0.469,
      0.41,
      0.826,
      0.426
    ],
    "crop_required": true,
    "overlay_required": true,
    "crop_path": "formula_crops/formula_019_p9.png",
    "overlay_path": "formula_overlays/formula_019_page_9.png",
    "section": "Method",
    "section_confidence": "medium",
    "section_reason": "reading_order_context: page 9",
    "block_source": "mineru25pro",
    "mineru_latex": "\\mathbf {Z} = \\mu_ {\\mathbf {Z}} \\tag {19}",
    "marker_latex": "",
    "final_latex": "\\mathbf {Z} = \\mu_ {\\mathbf {Z}} \\tag {19}",
    "final_origin": "mineru_latex",
    "risk_flags": []
  },
  {
    "formula_id": "formula_020",
    "block_id": "b0154",
    "page": 10,
    "bbox": [
      0.367,
      0.845,
      0.825,
      0.865
    ],
    "crop_required": true,
    "overlay_required": true,
    "crop_path": "formula_crops/formula_020_p10.png",
    "overlay_path": "formula_overlays/formula_020_page_10.png",
    "section": "Method",
    "section_confidence": "medium",
    "section_reason": "reading_order_context: page 10",
    "block_source": "mineru25pro",
    "mineru_latex": "\\mu_ {x + y} = \\mu_ {x} + \\mu_ {y} \\quad \\sigma_ {x + y} ^ {2} = \\sigma_ {x} ^ {2} + \\sigma_ {y} ^ {2} \\tag {20}",
    "marker_latex": "",
    "final_latex": "\\mu_ {x + y} = \\mu_ {x} + \\mu_ {y} \\quad \\sigma_ {x + y} ^ {2} = \\sigma_ {x} ^ {2} + \\sigma_ {y} ^ {2} \\tag {20}",
    "final_origin": "mineru_latex",
    "risk_flags": []
  },
  {
    "formula_id": "formula_021",
    "block_id": "b0156",
    "page": 10,
    "bbox": [
      0.431,
      0.891,
      0.826,
      0.917
    ],
    "crop_required": true,
    "overlay_required": true,
    "crop_path": "formula_crops/formula_021_p10.png",
    "overlay_path": "formula_overlays/formula_021_page_10.png",
    "section": "Method",
    "section_confidence": "medium",
    "section_reason": "reading_order_context: page 10",
    "block_source": "mineru25pro",
    "mineru_latex": "\\sigma_ {x + y} = \\sqrt {\\sigma_ {x} ^ {2} + \\sigma_ {y} ^ {2}} \\tag {21}",
    "marker_latex": "",
    "final_latex": "\\sigma_ {x + y} = \\sqrt {\\sigma_ {x} ^ {2} + \\sigma_ {y} ^ {2}} \\tag {21}",
    "final_origin": "mineru_latex",
    "risk_flags": []
  },
  {
    "formula_id": "formula_022",
    "block_id": "b0161",
    "page": 11,
    "bbox": [
      0.191,
      0.14,
      0.348,
      0.152
    ],
    "crop_required": true,
    "overlay_required": true,
    "crop_path": "formula_crops/formula_022_p11.png",
    "overlay_path": "formula_overlays/formula_022_page_11.png",
    "section": "Method",
    "section_confidence": "medium",
    "section_reason": "reading_order_context: page 11",
    "block_source": "mineru25pro",
    "mineru_latex": "n _ {\\text { windows }} \\leftarrow T _ {n} - w + 1",
    "marker_latex": "",
    "final_latex": "n _ {\\text { windows }} \\leftarrow T _ {n} - w + 1",
    "final_origin": "mineru_latex",
    "risk_flags": []
  },
  {
    "formula_id": "formula_023",
    "block_id": "b0162",
    "page": 11,
    "bbox": [
      0.191,
      0.153,
      0.468,
      0.168
    ],
    "crop_required": true,
    "overlay_required": true,
    "crop_path": "formula_crops/formula_023_p11.png",
    "overlay_path": "formula_overlays/formula_023_page_11.png",
    "section": "Method",
    "section_confidence": "medium",
    "section_reason": "reading_order_context: page 11",
    "block_source": "mineru25pro",
    "mineru_latex": "\\mu_ {\\mathbf {X}, \\text { temp }} \\leftarrow \\text { zeros } (n _ {\\text { windows }}, T _ {n}, d _ {\\mathcal {D}}) + \\text { NaN }",
    "marker_latex": "",
    "final_latex": "\\mu_ {\\mathbf {X}, \\text { temp }} \\leftarrow \\text { zeros } (n _ {\\text { windows }}, T _ {n}, d _ {\\mathcal {D}}) + \\text { NaN }",
    "final_origin": "mineru_latex",
    "risk_flags": []
  },
  {
    "formula_id": "formula_024",
    "block_id": "b0163",
    "page": 11,
    "bbox": [
      0.191,
      0.169,
      0.468,
      0.184
    ],
    "crop_required": true,
    "overlay_required": true,
    "crop_path": "formula_crops/formula_024_p11.png",
    "overlay_path": "formula_overlays/formula_024_page_11.png",
    "section": "Method",
    "section_confidence": "medium",
    "section_reason": "reading_order_context: page 11",
    "block_source": "mineru25pro",
    "mineru_latex": "\\sigma_ {\\mathbf {X}, \\text { temp }} ^ {2} \\leftarrow \\text { zeros } (n _ {\\text { windows }}, T _ {n}, d _ {\\mathcal {D}}) + \\text { NaN }",
    "marker_latex": "",
    "final_latex": "\\sigma_ {\\mathbf {X}, \\text { temp }} ^ {2} \\leftarrow \\text { zeros } (n _ {\\text { windows }}, T _ {n}, d _ {\\mathcal {D}}) + \\text { NaN }",
    "final_origin": "mineru_latex",
    "risk_flags": []
  },
  {
    "formula_id": "formula_025",
    "block_id": "b0165",
    "page": 11,
    "bbox": [
      0.216,
      0.199,
      0.331,
      0.212
    ],
    "crop_required": true,
    "overlay_required": true,
    "crop_path": "formula_crops/formula_025_p11.png",
    "overlay_path": "formula_overlays/formula_025_page_11.png",
    "section": "Method",
    "section_confidence": "medium",
    "section_reason": "reading_order_context: page 11",
    "block_source": "mineru25pro",
    "mineru_latex": "\\mathbf {X} \\leftarrow \\mathcal {S} [ i: w + i ]",
    "marker_latex": "",
    "final_latex": "\\mathbf {X} \\leftarrow \\mathcal {S} [ i: w + i ]",
    "final_origin": "mineru_latex",
    "risk_flags": []
  },
  {
    "formula_id": "formula_026",
    "block_id": "b0166",
    "page": 11,
    "bbox": [
      0.217,
      0.212,
      0.366,
      0.227
    ],
    "crop_required": true,
    "overlay_required": true,
    "crop_path": "formula_crops/formula_026_p11.png",
    "overlay_path": "formula_overlays/formula_026_page_11.png",
    "section": "Method",
    "section_confidence": "medium",
    "section_reason": "reading_order_context: page 11",
    "block_source": "mineru25pro",
    "mineru_latex": "(\\boldsymbol {\\mu} _ {\\mathbf {Z}}, \\log \\boldsymbol {\\sigma} _ {\\mathbf {Z}} ^ {2}) \\leftarrow q _ {\\phi} (\\mathbf {X})",
    "marker_latex": "",
    "final_latex": "(\\boldsymbol {\\mu} _ {\\mathbf {Z}}, \\log \\boldsymbol {\\sigma} _ {\\mathbf {Z}} ^ {2}) \\leftarrow q _ {\\phi} (\\mathbf {X})",
    "final_origin": "mineru_latex",
    "risk_flags": []
  },
  {
    "formula_id": "formula_027",
    "block_id": "b0167",
    "page": 11,
    "bbox": [
      0.217,
      0.227,
      0.35,
      0.24
    ],
    "crop_required": true,
    "overlay_required": true,
    "crop_path": "formula_crops/formula_027_p11.png",
    "overlay_path": "formula_overlays/formula_027_page_11.png",
    "section": "Method",
    "section_confidence": "medium",
    "section_reason": "reading_order_context: page 11",
    "block_source": "mineru25pro",
    "mineru_latex": "\\mathbf {C} \\leftarrow \\operatorname{MA} (\\mathbf {X}, \\mathbf {X}, \\boldsymbol {\\mu} _ {\\mathbf {Z}})",
    "marker_latex": "",
    "final_latex": "\\mathbf {C} \\leftarrow \\operatorname{MA} (\\mathbf {X}, \\mathbf {X}, \\boldsymbol {\\mu} _ {\\mathbf {Z}})",
    "final_origin": "mineru_latex",
    "risk_flags": []
  },
  {
    "formula_id": "formula_028",
    "block_id": "b0168",
    "page": 11,
    "bbox": [
      0.217,
      0.24,
      0.366,
      0.255
    ],
    "crop_required": true,
    "overlay_required": true,
    "crop_path": "formula_crops/formula_028_p11.png",
    "overlay_path": "formula_overlays/formula_028_page_11.png",
    "section": "Method",
    "section_confidence": "medium",
    "section_reason": "reading_order_context: page 11",
    "block_source": "mineru25pro",
    "mineru_latex": "\\left(\\boldsymbol {\\mu} _ {\\mathbf {X}}, \\log \\boldsymbol {\\sigma} _ {\\mathbf {X}} ^ {2}\\right) \\leftarrow p _ {\\theta} (\\mathbf {C})",
    "marker_latex": "",
    "final_latex": "\\left(\\boldsymbol {\\mu} _ {\\mathbf {X}}, \\log \\boldsymbol {\\sigma} _ {\\mathbf {X}} ^ {2}\\right) \\leftarrow p _ {\\theta} (\\mathbf {C})",
    "final_origin": "mineru_latex",
    "risk_flags": []
  },
  {
    "formula_id": "formula_029",
    "block_id": "b0169",
    "page": 11,
    "bbox": [
      0.216,
      0.255,
      0.388,
      0.269
    ],
    "crop_required": true,
    "overlay_required": true,
    "crop_path": "formula_crops/formula_029_p11.png",
    "overlay_path": "formula_overlays/formula_029_page_11.png",
    "section": "Method",
    "section_confidence": "medium",
    "section_reason": "reading_order_context: page 11",
    "block_source": "mineru25pro",
    "mineru_latex": "\\boldsymbol {\\mu} _ {\\mathbf {X}, \\text { temp }} [ i, i: i + w ] \\leftarrow \\boldsymbol {\\mu} _ {\\mathbf {X}}",
    "marker_latex": "",
    "final_latex": "\\boldsymbol {\\mu} _ {\\mathbf {X}, \\text { temp }} [ i, i: i + w ] \\leftarrow \\boldsymbol {\\mu} _ {\\mathbf {X}}",
    "final_origin": "mineru_latex",
    "risk_flags": []
  },
  {
    "formula_id": "formula_030",
    "block_id": "b0170",
    "page": 11,
    "bbox": [
      0.216,
      0.269,
      0.389,
      0.286
    ],
    "crop_required": true,
    "overlay_required": true,
    "crop_path": "formula_crops/formula_030_p11.png",
    "overlay_path": "formula_overlays/formula_030_page_11.png",
    "section": "Method",
    "section_confidence": "medium",
    "section_reason": "reading_order_context: page 11",
    "block_source": "mineru25pro",
    "mineru_latex": "\\sigma_ {\\mathbf {X}, \\text { temp }} ^ {2} [ i, i: i + w ] \\leftarrow \\sigma_ {\\mathbf {X}} ^ {2}",
    "marker_latex": "",
    "final_latex": "\\sigma_ {\\mathbf {X}, \\text { temp }} ^ {2} [ i, i: i + w ] \\leftarrow \\sigma_ {\\mathbf {X}} ^ {2}",
    "final_origin": "mineru_latex",
    "risk_flags": []
  },
  {
    "formula_id": "formula_031",
    "block_id": "b0172",
    "page": 11,
    "bbox": [
      0.191,
      0.299,
      0.372,
      0.314
    ],
    "crop_required": true,
    "overlay_required": true,
    "crop_path": "formula_crops/formula_031_p11.png",
    "overlay_path": "formula_overlays/formula_031_page_11.png",
    "section": "Method",
    "section_confidence": "medium",
    "section_reason": "reading_order_context: page 11",
    "block_source": "mineru25pro",
    "mineru_latex": "\\boldsymbol {\\mu} _ {\\mathcal {S}} \\leftarrow \\text { nanmean } (\\boldsymbol {\\mu} _ {\\mathbf {X}, \\text { temp }}, 0)",
    "marker_latex": "",
    "final_latex": "\\boldsymbol {\\mu} _ {\\mathcal {S}} \\leftarrow \\text { nanmean } (\\boldsymbol {\\mu} _ {\\mathbf {X}, \\text { temp }}, 0)",
    "final_origin": "mineru_latex",
    "risk_flags": []
  },
  {
    "formula_id": "formula_032",
    "block_id": "b0173",
    "page": 11,
    "bbox": [
      0.191,
      0.314,
      0.372,
      0.331
    ],
    "crop_required": true,
    "overlay_required": true,
    "crop_path": "formula_crops/formula_032_p11.png",
    "overlay_path": "formula_overlays/formula_032_page_11.png",
    "section": "Method",
    "section_confidence": "medium",
    "section_reason": "reading_order_context: page 11",
    "block_source": "mineru25pro",
    "mineru_latex": "\\sigma_ {S} ^ {2} \\leftarrow \\text { nanmean } (\\sigma_ {\\mathbf {X}, \\text { temp }} ^ {2}, 0)",
    "marker_latex": "",
    "final_latex": "\\sigma_ {S} ^ {2} \\leftarrow \\text { nanmean } (\\sigma_ {\\mathbf {X}, \\text { temp }} ^ {2}, 0)",
    "final_origin": "mineru_latex",
    "risk_flags": []
  },
  {
    "formula_id": "formula_033",
    "block_id": "b0174",
    "page": 11,
    "bbox": [
      0.191,
      0.332,
      0.366,
      0.346
    ],
    "crop_required": true,
    "overlay_required": true,
    "crop_path": "formula_crops/formula_033_p11.png",
    "overlay_path": "formula_overlays/formula_033_page_11.png",
    "section": "Method",
    "section_confidence": "medium",
    "section_reason": "reading_order_context: page 11",
    "block_source": "mineru25pro",
    "mineru_latex": "\\mathbf {s} _ {n} \\leftarrow - \\log p \\left(\\boldsymbol {\\mu} _ {\\mathcal {S}}, \\boldsymbol {\\sigma} _ {\\mathcal {S}} \\mid \\mathcal {S} _ {n}\\right)",
    "marker_latex": "",
    "final_latex": "\\mathbf {s} _ {n} \\leftarrow - \\log p \\left(\\boldsymbol {\\mu} _ {\\mathcal {S}}, \\boldsymbol {\\sigma} _ {\\mathcal {S}} \\mid \\mathcal {S} _ {n}\\right)",
    "final_origin": "mineru_latex",
    "risk_flags": []
  },
  {
    "formula_id": "formula_034",
    "block_id": "b0175",
    "page": 11,
    "bbox": [
      0.191,
      0.347,
      0.319,
      0.359
    ],
    "crop_required": true,
    "overlay_required": true,
    "crop_path": "formula_crops/formula_034_p11.png",
    "overlay_path": "formula_overlays/formula_034_page_11.png",
    "section": "Method",
    "section_confidence": "medium",
    "section_reason": "reading_order_context: page 11",
    "block_source": "mineru25pro",
    "mineru_latex": "l _ {n} \\leftarrow \\max \\left(\\mathbf {s} _ {n}\\right) > \\tau",
    "marker_latex": "",
    "final_latex": "l _ {n} \\leftarrow \\max \\left(\\mathbf {s} _ {n}\\right) > \\tau",
    "final_origin": "mineru_latex",
    "risk_flags": []
  },
  {
    "formula_id": "formula_035",
    "block_id": "b0218",
    "page": 13,
    "bbox": [
      0.304,
      0.827,
      0.826,
      0.861
    ],
    "crop_required": true,
    "overlay_required": true,
    "crop_path": "formula_crops/formula_035_p13.png",
    "overlay_path": "formula_overlays/formula_035_page_13.png",
    "section": "Experiments",
    "section_confidence": "medium",
    "section_reason": "reading_order_context: page 13",
    "block_source": "mineru25pro",
    "mineru_latex": "P = \\frac {N _ {\\mathrm{tp}}}{N _ {\\mathrm{tp}} + N _ {\\mathrm{fp}}} \\quad R = \\frac {N _ {\\mathrm{tp}}}{N _ {\\mathrm{tp}} + N _ {\\mathrm{fn}}} \\quad F _ {1} = 2 \\cdot \\frac {P \\cdot R}{P + R} \\tag {22}",
    "marker_latex": "",
    "final_latex": "P = \\frac {N _ {\\mathrm{tp}}}{N _ {\\mathrm{tp}} + N _ {\\mathrm{fp}}} \\quad R = \\frac {N _ {\\mathrm{tp}}}{N _ {\\mathrm{tp}} + N _ {\\mathrm{fn}}} \\quad F _ {1} = 2 \\cdot \\frac {P \\cdot R}{P + R} \\tag {22}",
    "final_origin": "mineru_latex",
    "risk_flags": []
  },
  {
    "formula_id": "formula_036",
    "block_id": "b0223",
    "page": 14,
    "bbox": [
      0.438,
      0.16,
      0.826,
      0.193
    ],
    "crop_required": true,
    "overlay_required": true,
    "crop_path": "formula_crops/formula_036_p14.png",
    "overlay_path": "formula_overlays/formula_036_page_14.png",
    "section": "Experiments",
    "section_confidence": "medium",
    "section_reason": "reading_order_context: page 14",
    "block_source": "mineru25pro",
    "mineru_latex": "A _ {\\mathrm{PR}} ^ {\\text { cont }} = \\int_ {0} ^ {1} P d R \\tag {23}",
    "marker_latex": "",
    "final_latex": "A _ {\\mathrm{PR}} ^ {\\text { cont }} = \\int_ {0} ^ {1} P d R \\tag {23}",
    "final_origin": "mineru_latex",
    "risk_flags": []
  },
  {
    "formula_id": "formula_037",
    "block_id": "b0225",
    "page": 14,
    "bbox": [
      0.398,
      0.227,
      0.826,
      0.268
    ],
    "crop_required": true,
    "overlay_required": true,
    "crop_path": "formula_crops/formula_037_p14.png",
    "overlay_path": "formula_overlays/formula_037_page_14.png",
    "section": "Experiments",
    "section_confidence": "medium",
    "section_reason": "reading_order_context: page 14",
    "block_source": "mineru25pro",
    "mineru_latex": "A _ {\\mathrm{PR}} ^ {\\mathrm{disc}} = \\sum_ {k = 1} ^ {K - 1} \\frac {P _ {k - 1} + P _ {k}}{2} \\Delta R _ {k} \\tag {24}",
    "marker_latex": "",
    "final_latex": "A _ {\\mathrm{PR}} ^ {\\mathrm{disc}} = \\sum_ {k = 1} ^ {K - 1} \\frac {P _ {k - 1} + P _ {k}}{2} \\Delta R _ {k} \\tag {24}",
    "final_origin": "mineru_latex",
    "risk_flags": []
  },
  {
    "formula_id": "formula_038",
    "block_id": "b0228",
    "page": 14,
    "bbox": [
      0.452,
      0.402,
      0.825,
      0.418
    ],
    "crop_required": true,
    "overlay_required": true,
    "crop_path": "formula_crops/formula_038_p14.png",
    "overlay_path": "formula_overlays/formula_038_page_14.png",
    "section": "Experiments",
    "section_confidence": "medium",
    "section_reason": "reading_order_context: page 14",
    "block_source": "mineru25pro",
    "mineru_latex": "\\delta = \\left| t _ {\\mathrm{p}} - t _ {\\mathrm{gt}} \\right| \\tag {25}",
    "marker_latex": "",
    "final_latex": "\\delta = \\left| t _ {\\mathrm{p}} - t _ {\\mathrm{gt}} \\right| \\tag {25}",
    "final_origin": "mineru_latex",
    "risk_flags": []
  },
  {
    "formula_id": "formula_039",
    "block_id": "b0230",
    "page": 14,
    "bbox": [
      0.415,
      0.506,
      0.826,
      0.547
    ],
    "crop_required": true,
    "overlay_required": true,
    "crop_path": "formula_crops/formula_039_p14.png",
    "overlay_path": "formula_overlays/formula_039_page_14.png",
    "section": "Experiments",
    "section_confidence": "medium",
    "section_reason": "reading_order_context: page 14",
    "block_source": "mineru25pro",
    "mineru_latex": "\\bar {\\delta} = \\frac {1}{N _ {\\mathrm{ts}} + N _ {\\mathrm{ss}}} \\sum_ {i = 1} ^ {N _ {\\mathrm{ts}} + N _ {\\mathrm{ss}}} \\delta_ {i} \\tag {26}",
    "marker_latex": "",
    "final_latex": "\\bar {\\delta} = \\frac {1}{N _ {\\mathrm{ts}} + N _ {\\mathrm{ss}}} \\sum_ {i = 1} ^ {N _ {\\mathrm{ts}} + N _ {\\mathrm{ss}}} \\delta_ {i} \\tag {26}",
    "final_origin": "mineru_latex",
    "risk_flags": []
  },
  {
    "formula_id": "formula_040",
    "block_id": "b0232",
    "page": 14,
    "bbox": [
      0.44,
      0.85,
      0.826,
      0.884
    ],
    "crop_required": true,
    "overlay_required": true,
    "crop_path": "formula_crops/formula_040_p14.png",
    "overlay_path": "formula_overlays/formula_040_page_14.png",
    "section": "Experiments",
    "section_confidence": "medium",
    "section_reason": "reading_order_context: page 14",
    "block_source": "mineru25pro",
    "mineru_latex": "P _ {\\mathrm{rc}} = \\frac {N _ {\\mathrm{tp} _ {\\mathrm{rc}}}}{N _ {\\mathrm{tp}} + N _ {\\mathrm{fp}}} \\tag {27}",
    "marker_latex": "",
    "final_latex": "P _ {\\mathrm{rc}} = \\frac {N _ {\\mathrm{tp} _ {\\mathrm{rc}}}}{N _ {\\mathrm{tp}} + N _ {\\mathrm{fp}}} \\tag {27}",
    "final_origin": "mineru_latex",
    "risk_flags": []
  }
]